FiNoodle/__init__.py
FiNoodle/cli.py
FiNoodle/exportQuestions.py
FiNoodle/moodle_compile/__init__.py
FiNoodle/moodle_compile/compile.py
FiNoodle/moodle_compile/parser/Answer.py
FiNoodle/moodle_compile/parser/Category.py
FiNoodle/moodle_compile/parser/File.py
FiNoodle/moodle_compile/parser/Question.py
FiNoodle/moodle_compile/parser/TestCase.py
FiNoodle/moodle_compile/parser/__init__.py
FiNoodle/moodle_compile/templates/__init__.py
FiNoodle/moodle_compile/templates/coderunner.xml
FiNoodle/moodle_compile/templates/description.xml
FiNoodle/moodle_compile/templates/multiplechoice.xml
FiNoodle/moodle_compile/templates/quiz.xml
FiNoodle/moodle_compile/templates/shortanswer.xml
FiNoodle-0.1.69.dist-info/LICENCE
FiNoodle-0.1.69.dist-info/METADATA
FiNoodle-0.1.69.dist-info/WHEEL
FiNoodle-0.1.69.dist-info/top_level.txt
FiNoodle-0.1.69.dist-info/RECORD
