Metadata-Version: 2.1
Name: FiNoodle
Version: 0.1.69
Summary: A small transpiler that converts human-readable text and TOML file formats representing Moodle questions to Moodle XML
Home-page: https://github.com/uoa-compsci399-s2-2022/Finale
Author: Team Finale
License: MIT License
Classifier: Development Status :: 1 - Planning
Classifier: Topic :: Utilities
Classifier: Intended Audience :: Education
Classifier: Programming Language :: Python :: 3
Classifier: License :: OSI Approved :: MIT License
Classifier: Operating System :: OS Independent
License-File: LICENCE
